potc_treevalue/__init__.py
potc_treevalue/config/__init__.py
potc_treevalue/config/meta.py
potc_treevalue/plugin/__init__.py
potc_treevalue/plugin/rules.py
potc_treevalue/plugin/treevalue.py
potc_treevalue-0.0.1.dist-info/LICENSE
potc_treevalue-0.0.1.dist-info/METADATA
potc_treevalue-0.0.1.dist-info/WHEEL
potc_treevalue-0.0.1.dist-info/entry_points.txt
potc_treevalue-0.0.1.dist-info/top_level.txt
potc_treevalue-0.0.1.dist-info/RECORD
